AUTHORS.rst
CONTRIBUTING.rst
HISTORY.rst
LICENSE
MANIFEST.in
README.rst
setup.cfg
setup.py
t_dict/__init__.py
t_dict/t_dict.py
t_dict.egg-info/PKG-INFO
t_dict.egg-info/SOURCES.txt
t_dict.egg-info/dependency_links.txt
t_dict.egg-info/not-zip-safe
t_dict.egg-info/requires.txt
t_dict.egg-info/top_level.txt
tests/__init__.py
tests/test_t_dict.py