Metadata-Version: 1.1
Name: t-dict
Version: 0.1.1
Summary: Traversing and Querying Dicts the easy way
Home-page: https://github.com/vandersonmota/t_dict
Author: Vanderson Mota
Author-email: vanderson.mota@gmail.com
License: BSD
Keywords: t_dict
Platform: UNKNOWN
Classifier: Development Status :: 2 - Pre-Alpha
Classifier: Intended Audience :: Developers
Classifier: License :: OSI Approved :: BSD License
Classifier: Natural Language :: English
Classifier: Programming Language :: Python :: 2
Classifier: Programming Language :: Python :: 2.6
Classifier: Programming Language :: Python :: 2.7
Classifier: Programming Language :: Python :: 3
Classifier: Programming Language :: Python :: 3.3
Classifier: Programming Language :: Python :: 3.4
